{
  "routes": [
    {
      "method": "GET",
      "path": "/seances",
      "handler": "seance.find",
      "config": {
        "policies": []
      }
    },
    {
      "method": "GET",
      "path": "/seances/count",
      "handler": "seance.count",
      "config": {
        "policies": []
      }
    },
    {
      "method": "GET",
      "path": "/seances/:id",
      "handler": "seance.findOne",
      "config": {
        "policies": []
      }
    },
    {
      "method": "POST",
      "path": "/seances",
      "handler": "seance.create",
      "config": {
        "policies": []
      }
    },
    {
      "method": "PUT",
      "path": "/seances/:id",
      "handler": "seance.update",
      "config": {
        "policies": []
      }
    },
    {
      "method": "DELETE",
      "path": "/seances/:id",
      "handler": "seance.delete",
      "config": {
        "policies": []
      }
    }
  ]
}
